{
  "project_info": {
    "project_number": "991330551936",
    "project_id": "shopat-8fe6c",
    "storage_bucket": "shopat-8fe6c.appspot.com"
  },
  "client": [
    {
      "client_info": {
        "mobilesdk_app_id": "1:991330551936:android:cca3f6aea0c00f2260fe65",
        "android_client_info": {
          "package_name": "com.example.shopat"
        }
      },
      "oauth_client": [
        {
          "client_id": "991330551936-5bk5cl2k8t051cm2r3b3tamt2nm864fn.apps.googleusercontent.com",
          "client_type": 1,
          "android_info": {
            "package_name": "com.example.shopat",
            "certificate_hash": "c9dd4bbb5a10c99df56371309142967cb2710e36"
          }
        },
        {
          "client_id": "991330551936-a72a5d0k8e4jdouanbvi0fjmomobgo7v.apps.googleusercontent.com",
          "client_type": 1,
          "android_info": {
            "package_name": "com.example.shopat",
            "certificate_hash": "cdbec65a8eedb3d3db957fb4972a17484f3183d6"
          }
        },
        {
          "client_id": "991330551936-ka0r78uk76oq0suml27mg8ruedn2c2v1.apps.googleusercontent.com",
          "client_type": 1,
          "android_info": {
            "package_name": "com.example.shopat",
            "certificate_hash": "68b8e617000e4d50b99167813bf92a367ea75967"
          }
        },
        {
          "client_id": "991330551936-1usc0imjeiqjatlsfk976j0bgqq4q35m.apps.googleusercontent.com",
          "client_type": 3
        }
      ],
      "api_key": [
        {
          "current_key": "AIzaSyBNQ5WmcaFyscubR9hYnTTML83pTxeG1gg"
        }
      ],
      "services": {
        "appinvite_service": {
          "other_platform_oauth_client": [
            {
              "client_id": "991330551936-1usc0imjeiqjatlsfk976j0bgqq4q35m.apps.googleusercontent.com",
              "client_type": 3
            }
          ]
        }
      }
    },
    {
      "client_info": {
        "mobilesdk_app_id": "1:991330551936:android:2b517318250a329a60fe65",
        "android_client_info": {
          "package_name": "com.example.shopat_seller"
        }
      },
      "oauth_client": [
        {
          "client_id": "991330551936-sjbd5tl55shftvck982mkmvplfr1hqdq.apps.googleusercontent.com",
          "client_type": 1,
          "android_info": {
            "package_name": "com.example.shopat_seller",
            "certificate_hash": "cdbec65a8eedb3d3db957fb4972a17484f3183d6"
          }
        },
        {
          "client_id": "991330551936-1usc0imjeiqjatlsfk976j0bgqq4q35m.apps.googleusercontent.com",
          "client_type": 3
        }
      ],
      "api_key": [
        {
          "current_key": "AIzaSyBNQ5WmcaFyscubR9hYnTTML83pTxeG1gg"
        }
      ],
      "services": {
        "appinvite_service": {
          "other_platform_oauth_client": [
            {
              "client_id": "991330551936-1usc0imjeiqjatlsfk976j0bgqq4q35m.apps.googleusercontent.com",
              "client_type": 3
            }
          ]
        }
      }
    }
  ],
  "configuration_version": "1"
}